{
  "headline": "Opinion | Joe Heller cartoon on President Donald Trump’s 100th day in office - The Washington Post",
  "context": [
    "Democracy Dies in Darkness",
    "OpinionsEditorialsColumnsGuest OpinionsCartoonsLetters to the EditorSubmit a Guest OpinionSubmit a Letter"
  ],
  "annotations": [
    {
      "paragraph": "OpinionsEditorialsColumnsGuest OpinionsCartoonsLetters to the EditorSubmit a Guest OpinionSubmit a Letter",
      "reason": "This is a list of sections and submission options, not related to the cartoon or its content.",
      "label": 0
    },
    {
      "paragraph": "Opinion",
      "reason": "This is a section header and does not provide information about the cartoon.",
      "label": 0
    },
    {
      "paragraph": "April 29, 2025",
      "reason": "This is a date and does not provide information about the cartoon.",
      "label": 0
    },
    {
      "paragraph": "By  Joe Heller",
      "reason": "This is an author byline and does not provide information about the cartoon.",
      "label": 0
    },
    {
      "paragraph": "The latest editorial cartoons",
      "reason": "This is a general statement about editorial cartoons and does not provide specific information about the cartoon in question.",
      "label": 0
    },
    {
      "paragraph": "HAND CURATED",
      "reason": "This is a label or category tag, not content.",
      "label": 0
    },
    {
      "paragraph": "Opinion",
      "reason": "This is a label or category tag, not content.",
      "label": 0
    },
    {
      "paragraph": "The Met Gala checklist for attendees",
      "reason": "This is unrelated to the headline about Joe Heller's cartoon on Trump's 100th day.",
      "label": 0
    },
    {
      "paragraph": "Earlier today",
      "reason": "This is an incomplete statement with no context or information.",
      "label": 0
    },
    {
      "paragraph": "Opinion",
      "reason": "This is a label or category tag, not content.",
      "label": 0
    },
    {
      "paragraph": "The diversion",
      "reason": "This is a vague and unrelated phrase with no context or information.",
      "label": 0
    },
    {
      "paragraph": "May 1, 2025",
      "reason": "This is a date and does not provide any relevant information.",
      "label": 0
    },
    {
      "paragraph": "Opinion",
      "reason": "This is a section label and does not provide any relevant information.",
      "label": 0
    },
    {
      "paragraph": "Cartoon by Al Goodwyn",
      "reason": "This is a credit line for a cartoon and does not provide relevant information.",
      "label": 0
    },
    {
      "paragraph": "April 29, 2025",
      "reason": "This is a date and does not provide any relevant information.",
      "label": 0
    }
  ]
}